setup.py
kinesis_tail/__init__.py
kinesis_tail/cli.py
ktail.egg-info/PKG-INFO
ktail.egg-info/SOURCES.txt
ktail.egg-info/dependency_links.txt
ktail.egg-info/entry_points.txt
ktail.egg-info/requires.txt
ktail.egg-info/top_level.txt
ktail.egg-info/zip-safe
scripts/ktail