Metadata-Version: 1.1
Name: ktail
Version: 0.1.1
Summary: AWS Kinesis tail
Home-page: https://github.com/marco-hoyer/ktail
Author: Marco Hoyer
Author-email: marco_hoyer@gmx.de
License: APACHE LICENSE, VERSION 2.0
Platform: UNKNOWN
Classifier: Development Status :: 4 - Beta
Classifier: Environment :: Console
Classifier: Intended Audience :: Developers
Classifier: Intended Audience :: System Administrators
Classifier: License :: OSI Approved :: Apache Software License
Classifier: Programming Language :: Python
Classifier: Topic :: System :: Systems Administration
